{
    "version": "0.7.1",
    "architecture": {
        "64bit": {
            "url": "https://github.com/tilt-dev/ctlptl/releases/download/v0.7.1/ctlptl.0.7.1.windows.x86_64.zip",
            "bin": [
                "ctlptl.exe"
            ],
            "hash": "61eceba4a42eee7375f81c7061eec537241c2db37e10414602bb39dad36fe7fe"
        }
    },
    "homepage": "https://ctlptl.dev/",
    "license": "Apache-2.0",
    "description": "Making local Kubernetes clusters easy to set up and tear down"
}