{
    "version": "0.8.7",
    "architecture": {
        "64bit": {
            "url": "https://github.com/tilt-dev/ctlptl/releases/download/v0.8.7/ctlptl.0.8.7.windows.x86_64.zip",
            "bin": [
                "ctlptl.exe"
            ],
            "hash": "2113e7fb6bba22bb36c3dbc31c7bf73383c699fae97b4d756f5f0dbd7088ea30"
        }
    },
    "homepage": "https://ctlptl.dev/",
    "license": "Apache-2.0",
    "description": "Making local Kubernetes clusters easy to set up and tear down"
}