{
    "version": "0.4.2",
    "architecture": {
        "64bit": {
            "url": "https://github.com/tilt-dev/ctlptl/releases/download/v0.4.2/ctlptl.0.4.2.windows.x86_64.zip",
            "bin": [
                "ctlptl.exe"
            ],
            "hash": "d362dba168ed8f3a8d9397137612fdf501ee2408661032f66270cc340e05e47e"
        }
    },
    "homepage": "https://ctlptl.dev/",
    "license": "Apache-2.0",
    "description": "Making local Kubernetes clusters easy to set up and tear down"
}